[{"name": "KV Cable Squat", "image": "https://www.bodybuilding.com/images/2018/august/cable-squat-a.jpg", "targeted_muscle": "Quadriceps", "equipment_used": "Cable", "avg_rating": "n/a", "details_page": "KV Cable Squat"}, {"name": "KV Cable Kick-Back", "image": "https://www.bodybuilding.com/images/2018/august/cable-kick-back-a.jpg", "targeted_muscle": "Abdominals", "equipment_used": "Cables", "avg_rating": "n/a", "details_page": "KV Cable Kick-Back"}, {"name": "KV Romanian Deadlift with Kettlebell", "image": "https://www.bodybuilding.com/images/2018/september/kettlebell-romanian-deadlift-a.jpg", "targeted_muscle": "Lower Back", "equipment_used": "Kettlebells", "avg_rating": "n/a", "details_page": "KV Romanian Deadlift with Kettlebell"}, {"name": "LD Cable One-Arm Upright Row", "image": "https://www.bodybuilding.com/images/2016/august/cable-upright-row1.jpg", "targeted_muscle": "Triceps", "equipment_used": "Cable", "avg_rating": "n/a", "details_page": "LD Cable One-Arm Upright Row"}, {"name": "Wide-Grip Barbell Incline Row", "image": "https://www.bodybuilding.com/images/2018/october/wide-grip-barbell-incline-row-a.jpg", "targeted_muscle": "Abdominals", "equipment_used": "", "avg_rating": "n/a", "details_page": "Wide-Grip Barbell Incline Row"}, {"name": "Assisted Single-Arm Pull-Up", "image": "https://www.bodybuilding.com/images/2018/october/assisted-single-arm-chin-up-a.jpg", "targeted_muscle": "Lats", "equipment_used": "Other", "avg_rating": "n/a", "details_page": "Assisted Single-Arm Pull-Up"}, {"name": "Assisted Single-Arm Chin-Up", "image": "https://www.bodybuilding.com/images/2018/october/assisted-single-arm-pull-up-a.jpg", "targeted_muscle": "Lats", "equipment_used": "Other", "avg_rating": "n/a", "details_page": "Assisted Single-Arm Chin-Up"}, {"name": "Rhomboid Reverse Fly", "image": "https://www.bodybuilding.com/images/2018/october/rhomboid-reverse-fly-b.jpg", "targeted_muscle": "Abdominals", "equipment_used": "", "avg_rating": "n/a", "details_page": "Rhomboid Reverse Fly"}, {"name": "Holt Landmine Chest To Sit-Up", "image": "https://www.bodybuilding.com/images/2018/october/landmine-chest-press-to-sit-up-a.jpg", "targeted_muscle": "Abdominals", "equipment_used": "Landmine", "avg_rating": "n/a", "details_page": "Holt Landmine Chest To Sit-Up"}, {"name": "Holt Landmine Bent-Over Row", "image": "https://www.bodybuilding.com/images/2018/october/landmine-bent-over-row-a.jpg", "targeted_muscle": "Abdominals", "equipment_used": "", "avg_rating": "n/a", "details_page": "Holt Landmine Bent-Over Row"}, {"name": "Holt Landmine Twist", "image": "https://www.bodybuilding.com/images/2018/october/landmine-twist-a.jpg", "targeted_muscle": "Abdominals", "equipment_used": "", "avg_rating": "n/a", "details_page": "Holt Landmine Twist"}, {"name": "Holt Landmine Pull And Press", "image": "https://www.bodybuilding.com/images/2018/october/landmine-pull-and-press-b.jpg", "targeted_muscle": "Abdominals", "equipment_used": "", "avg_rating": "n/a", "details_page": "Holt Landmine Pull And Press"}, {"name": "Holt Landmine Lunge To Press", "image": "https://www.bodybuilding.com/images/2018/october/landmine-lunge-to-press-a.jpg", "targeted_muscle": "Abdominals", "equipment_used": "", "avg_rating": "n/a", "details_page": "Holt Landmine Lunge To Press"}, {"name": "Holt Landmine Burpee", "image": "https://www.bodybuilding.com/images/2018/october/landmine-burpee-a.jpg", "targeted_muscle": "Abdominals", "equipment_used": "", "avg_rating": "n/a", "details_page": "Holt Landmine Burpee"}, {"name": "Holman Towel Reverse Plank Alternating Heel Pull-in", "image": "https://www.bodybuilding.com/images/2018/20-minute-fit/20min-fit-xdb-reverse-straight-plank-with-alternating-heel-pull-in-a.jpg", "targeted_muscle": "Abdominals", "equipment_used": "Other", "avg_rating": "n/a", "details_page": "Holman Towel Reverse Plank Alternating Heel Pull-in"}]